LICENSE
MANIFEST.in
setup.py
balbec/__init__.py
balbec/balbec_twisted.py
balbec/filebackend.py
balbec/htmlhandler.py
balbec/jsonhandler.py
balbec/livestatusbackend.py
balbec/mysqlbackend.py
balbec/objects.py
balbec/xmlhandler.py
balbec/schema/config.xsd
balbec/schema/old_config.xsd
balbec/static/index.html
balbec/static/mockup.html
python_nagios_frontend.egg-info/PKG-INFO
python_nagios_frontend.egg-info/SOURCES.txt
python_nagios_frontend.egg-info/dependency_links.txt
python_nagios_frontend.egg-info/entry_points.txt
python_nagios_frontend.egg-info/requires.txt
python_nagios_frontend.egg-info/top_level.txt