Metadata-Version: 1.0
Name: python-nagios-frontend
Version: 0.8.7
Summary: A nagios frontend, which makes things looks nicer. Provides HTML, JSON and XML. Based on the excellent package "balbec".
Home-page: https://github.com/KristianOellegaard/python-nagios-frontend
Author: Magnus Kulke, Kristian Oellegaard, Ales Kocjancic
Author-email: kristian@oellegaard.com
License: AGPL
Platform: UNKNOWN
